AUTHORS.rst
CHANGES.rst
LICENSE.rst
MANIFEST.in
README.rst
pyproject.toml
setup.cfg
setup.py
bmi_wavewatch3/__init__.py
bmi_wavewatch3/_version.py
bmi_wavewatch3/bmi.py
bmi_wavewatch3/cli.py
bmi_wavewatch3/downloader.py
bmi_wavewatch3/errors.py
bmi_wavewatch3/source.py
bmi_wavewatch3/wavewatch3.py
bmi_wavewatch3.egg-info/PKG-INFO
bmi_wavewatch3.egg-info/SOURCES.txt
bmi_wavewatch3.egg-info/dependency_links.txt
bmi_wavewatch3.egg-info/entry_points.txt
bmi_wavewatch3.egg-info/requires.txt
bmi_wavewatch3.egg-info/top_level.txt
tests/test_cli.py
tests/test_url.py
tests/test_wavewatch3.py