Metadata-Version: 2.1
Name: bmi-wavewatch3
Version: 0.1.1
Summary: Fetch WaveWatch3 data.
Author: The CSDMS team
Author-email: mcflugen@gmail.com
Maintainer: The CSDMS team
Maintainer-email: mcflugen@gmail.com
License: The MIT License (MIT)
Project-URL: homepage, https://github.com/csdms
Project-URL: documentation, https://github.com/csdms/bmi-wave-watch-3/blob/main/README.rst
Project-URL: repository, https://github.com/csdms/bmi-wave-watch-3
Project-URL: changelog, https://github.com/csdms/bmi-wave-watch-3/blob/main/CHANGES.rst
Keywords: bmi,wavewatch,data,grib
Classifier: Development Status :: 4 - Beta
Classifier: Intended Audience :: Science/Research
Classifier: License :: OSI Approved :: MIT License
Classifier: Operating System :: OS Independent
Classifier: Programming Language :: Cython
Classifier: Programming Language :: Python :: 3.8
Classifier: Programming Language :: Python :: 3.9
Classifier: Programming Language :: Python :: 3.10
Classifier: Programming Language :: Python :: 3
Classifier: Programming Language :: Python :: Implementation :: CPython
Classifier: Topic :: Scientific/Engineering :: Physics
Requires-Python: >=3.8
Provides-Extra: dev
Provides-Extra: testing
Provides-Extra: doc
License-File: LICENSE.rst
License-File: AUTHORS.rst
